web_analyser/__init__.py
web_analyser/web_analyser.py
web_analyser/helpers/__init__.py
web_analyser/helpers/analysis.py
web_analyser/helpers/recon.py
web_analyser/utils/__init__.py
web_analyser/utils/constants.py
web_analyser/utils/context.py
web_analyser/utils/log.py
web_analyser/utils/utils.py
web_ctf_analyser-0.0.5.dist-info/LICENSE
web_ctf_analyser-0.0.5.dist-info/METADATA
web_ctf_analyser-0.0.5.dist-info/WHEEL
web_ctf_analyser-0.0.5.dist-info/entry_points.txt
web_ctf_analyser-0.0.5.dist-info/top_level.txt
web_ctf_analyser-0.0.5.dist-info/RECORD
