Metadata-Version: 2.1
Name: web-ctf-analyser
Version: 0.0.5
Summary: A website analyser for CTF challenges
Home-page: https://github.com/ir0nstone/web-analyser
Author: Andrej Ljubic
Author-email: andrej.ljubic05@hotmail.com
Keywords: pypi,cicd,python
Classifier: Development Status :: 1 - Planning
Classifier: Intended Audience :: Developers
Classifier: Programming Language :: Python :: 3
Classifier: Operating System :: Unix
Classifier: Operating System :: MacOS :: MacOS X
Classifier: Operating System :: Microsoft :: Windows
License-File: LICENSE
Requires-Dist: colorama
Requires-Dist: beautifulsoup4
Requires-Dist: requests
Requires-Dist: argparse
